<?xml version="1.0"?>
<entry xmlns="http://www.w3.org/2005/Atom"
       xmlns:dcterms="http://purl.org/dc/terms/">
   <dcterms:source>http://www.tarki.hu/cgi-bin/katalogus/tarkimain_en.pl?sorszam=TDATA-A89</dcterms:source>
   <dcterms:title>Social Mobility in the United Kingdom 1972.</dcterms:title>
   <dcterms:creator>Merkl, Ildikó</dcterms:creator>
   <dcterms:bibliographicCitation>TÁRKI Joint Research Center</dcterms:bibliographicCitation>
   <dcterms:date>2009-04-09</dcterms:date>
   <dcterms:subject>TÁRKI Joint Research Center  TDATA-A89: Social Mobility in the United Kingdom 1972.. data sheet. Version: 2009-04-09</dcterms:subject>
   <dcterms:creator>Goldthorp, John</dcterms:creator>
   <dcterms:contributor>Nuffield College</dcterms:contributor>
   <dcterms:contributor>Nuffield College</dcterms:contributor>
   <dcterms:subject>1.0</dcterms:subject>
   <dcterms:description>occupation, level of education, political attitudes of the respondents and their parents at different times</dcterms:description>
	<dcterms:subject>mass political behavior, attitudes</dcterms:subject>
	<dcterms:subject>migration</dcterms:subject>
	<dcterms:subject>equality and inequality</dcterms:subject>
	<dcterms:subject>family life, marriage, relationship</dcterms:subject>
	<dcterms:subject>social and occupational mobility</dcterms:subject>
	<dcterms:subject>labour and employment</dcterms:subject>
	<dcterms:subject>demography</dcterms:subject>
	<dcterms:subject>social stratification and groupings</dcterms:subject>
	<dcterms:subject>cultural and national identity</dcterms:subject>
	<dcterms:subject>education, school</dcterms:subject>
	<dcterms:subject>local society, region</dcterms:subject>
	<dcterms:subject>income, property and savings</dcterms:subject>
	<dcterms:subject>time use</dcterms:subject>
	<dcterms:subject>psychology</dcterms:subject>
	<dcterms:subject>cultural activities and participation</dcterms:subject>
	<dcterms:subject>political institutions, public administration</dcterms:subject>
	<dcterms:subject>social conditions and indicators</dcterms:subject>
   <dcterms:subject>1972</dcterms:subject>
   <dcterms:coverage>England, Wales</dcterms:coverage>
   <dcterms:subject>person</dcterms:subject>
   <dcterms:subject>survey data</dcterms:subject>
   <dcterms:subject>cross-section</dcterms:subject>
   <dcterms:subject>Stratified sample. 12598 males between 20-64 years were interviewed in England and Wales.</dcterms:subject>
   <dcterms:subject>face-to-face interview</dcterms:subject>
   <dcterms:subject>A</dcterms:subject>
   <dcterms:rights>Publications based on TÁRKI data collections should acknowledge those sources, primary investigators and depositors.</dcterms:rights>
   <dcterms:subject>10309</dcterms:subject>
   <dcterms:subject>1082</dcterms:subject>
	<dcterms:subject>SPSS portable datafile</dcterms:subject>
</entry>