<?xml version="1.0"?>
<entry xmlns="http://www.w3.org/2005/Atom"
       xmlns:dcterms="http://purl.org/dc/terms/">
   <dcterms:source>http://www.tarki.hu/cgi-bin/katalogus/tarkimain_en.pl?sorszam=TDATA-B97</dcterms:source>
   <dcterms:title>World Exhibition 1989/2. Hungarian popular opinion about the planned world exhibition.</dcterms:title>
   <dcterms:creator>Merkl, Ildikó</dcterms:creator>
   <dcterms:bibliographicCitation>TÁRKI Joint Research Center</dcterms:bibliographicCitation>
   <dcterms:date>2007-01-19</dcterms:date>
   <dcterms:subject>TÁRKI Joint Research Center  TDATA-B97: World Exhibition 1989/2. Hungarian popular opinion about the planned world exhibition.. data sheet. Version: 2007-01-19</dcterms:subject>
   <dcterms:creator>Szurkos, Mária</dcterms:creator>
   <dcterms:contributor>Hungarian Public Opinion Research Institute</dcterms:contributor>
   <dcterms:contributor>TÁRKI Joint Research Center</dcterms:contributor>
   <dcterms:contributor>TÁRKI Social Research Institute Inc.</dcterms:contributor>
   <dcterms:subject>1.1</dcterms:subject>
   <dcterms:subject>2004-02-00: the labels of the data file are corrected and complemented</dcterms:subject>
   <dcterms:description>opinions about World Exhibition; citizen block</dcterms:description>
	<dcterms:subject>religion and values</dcterms:subject>
	<dcterms:subject>political institutions, public administration</dcterms:subject>
	<dcterms:subject>business/industrial management and organisation</dcterms:subject>
	<dcterms:subject>society and culture</dcterms:subject>
	<dcterms:subject>social conditions and indicators</dcterms:subject>
	<dcterms:subject>mass political behavior, attitudes</dcterms:subject>
	<dcterms:subject>economic conditions and indicators</dcterms:subject>
	<dcterms:subject>demography</dcterms:subject>
   <dcterms:subject>1989-02-24  1989-03-21</dcterms:subject>
   <dcterms:coverage>Hungary</dcterms:coverage>
   <dcterms:subject>person</dcterms:subject>
   <dcterms:subject>survey data</dcterms:subject>
   <dcterms:subject>cross-section</dcterms:subject>
   <dcterms:subject>A random national representative sample of the adult population.</dcterms:subject>
   <dcterms:subject>face-to-face interview</dcterms:subject>
   <dcterms:subject>A</dcterms:subject>
   <dcterms:rights>Publications based on TÁRKI data collections should acknowledge those sources, primary investigators and depositors.</dcterms:rights>
   <dcterms:subject>997</dcterms:subject>
   <dcterms:subject>279</dcterms:subject>
	<dcterms:subject>SPSS portable datafile</dcterms:subject>
	<dcterms:subject>other study-related materials:</dcterms:subject>
	<dcterms:subject>Hungarian questionnaire</dcterms:subject>
	<dcterms:subject>English questionnaire</dcterms:subject>
</entry>