<?xml version="1.0"?>
<entry xmlns="http://www.w3.org/2005/Atom"
       xmlns:dcterms="http://purl.org/dc/terms/">
   <dcterms:source>http://www.tarki.hu/cgi-bin/katalogus/tarkimain_en.pl?sorszam=TDATA-D15</dcterms:source>
   <dcterms:title>ISSP 1999. Social Inequality III. Hungarian data.</dcterms:title>
   <dcterms:creator>Merkl, Ildikó</dcterms:creator>
   <dcterms:bibliographicCitation>TÁRKI Joint Research Center</dcterms:bibliographicCitation>
   <dcterms:date>2009-04-09</dcterms:date>
   <dcterms:subject>TÁRKI Joint Research Center  TDATA-D15: ISSP 1999. Social Inequality III. Hungarian data.. data sheet. Version: 2009-04-09</dcterms:subject>
   <dcterms:creator>Róbert, Péter</dcterms:creator>
   <dcterms:contributor>TÁRKI Social Research Institute Inc.</dcterms:contributor>
   <dcterms:contributor>TÁRKI Joint Research Center</dcterms:contributor>
   <dcterms:contributor>TÁRKI Social Research Institute Inc.</dcterms:contributor>
   <dcterms:subject>1.0</dcterms:subject>
   <dcterms:description>perception of income differences and opinions about ways to eliminate them, social structure, changes in social status, mobility, change of economic order, workplace</dcterms:description>
	<dcterms:subject>social stratification and groupings</dcterms:subject>
	<dcterms:subject>education, school</dcterms:subject>
	<dcterms:subject>economic conditions and indicators</dcterms:subject>
	<dcterms:subject>equality and inequality</dcterms:subject>
	<dcterms:subject>political institutions, public administration</dcterms:subject>
	<dcterms:subject>business/industrial management and organisation</dcterms:subject>
	<dcterms:subject>family life, marriage, relationship</dcterms:subject>
	<dcterms:subject>economic systems and development</dcterms:subject>
	<dcterms:subject>social behaviour and attitudes</dcterms:subject>
	<dcterms:subject>housing</dcterms:subject>
	<dcterms:subject>income, property and savings</dcterms:subject>
	<dcterms:subject>consumption/consumer behavior</dcterms:subject>
	<dcterms:subject>science and technology</dcterms:subject>
	<dcterms:subject>social conditions and indicators</dcterms:subject>
	<dcterms:subject>religion and values</dcterms:subject>
	<dcterms:subject>social and occupational mobility</dcterms:subject>
	<dcterms:subject>mass political behavior, attitudes</dcterms:subject>
	<dcterms:subject>labour and employment</dcterms:subject>
   <dcterms:subject>1999-11-19  1999-11-28</dcterms:subject>
   <dcterms:coverage>Hungary</dcterms:coverage>
   <dcterms:subject>person</dcterms:subject>
   <dcterms:subject>survey data</dcterms:subject>
   <dcterms:subject>time-series</dcterms:subject>
   <dcterms:subject>A multi-stage proportionally stratified random probability sample representative of the Hungarian adult population. Unsuccessful inquiries were substituted with supplementary addresses, where persons to be interviewed were selected on the basis of the Leslie Kish key.</dcterms:subject>
   <dcterms:subject>face-to-face interview</dcterms:subject>
   <dcterms:subject>B</dcterms:subject>
   <dcterms:rights>Publications based on TÁRKI data collections should acknowledge those sources, primary investigators and depositors.</dcterms:rights>
   <dcterms:subject>1208</dcterms:subject>
   <dcterms:subject>209</dcterms:subject>
	<dcterms:subject>SPSS portable datafile</dcterms:subject>
	<dcterms:subject>other study-related materials:</dcterms:subject>
	<dcterms:subject>Hungarian questionnaire</dcterms:subject>
	<dcterms:subject>Hungarian documentation</dcterms:subject>
</entry>