<?xml version="1.0"?>
<entry xmlns="http://www.w3.org/2005/Atom"
       xmlns:dcterms="http://purl.org/dc/terms/">
   <dcterms:source>http://www.tarki.hu/cgi-bin/katalogus/tarkimain_en.pl?sorszam=TDATA-D96</dcterms:source>
   <dcterms:title>TÁRKI Omnibus 1999/5. Social-political attitudes in Hungary among the adult population.</dcterms:title>
   <dcterms:creator>Zsadányi-Nagy, Csaba</dcterms:creator>
   <dcterms:bibliographicCitation>TÁRKI Joint Research Center</dcterms:bibliographicCitation>
   <dcterms:date>2007-01-19</dcterms:date>
   <dcterms:subject>TÁRKI Joint Research Center  TDATA-D96: TÁRKI Omnibus 1999/5. Social-political attitudes in Hungary among the adult population.. data sheet. Version: 2007-01-19</dcterms:subject>
	<dcterms:creator>1.  <a href="http://www.tarki.hu/cgi-bin/katalogus/tarkiser_en.pl?kut=Gazso__Tibor">Gazsó, Tibor</a></dcterms:creator>
	<dcterms:creator>2.  <a href="http://www.tarki.hu/cgi-bin/katalogus/tarkiser_en.pl?kut=Toth__Zsolt">Tóth, Zsolt</a></dcterms:creator>
	<dcterms:creator>3.  <a href="http://www.tarki.hu/cgi-bin/katalogus/tarkiser_en.pl?kut=Pongracz__Tiborne">Pongrácz, Tiborné</a></dcterms:creator>
   <dcterms:contributor>TÁRKI Social Research Institute Inc.</dcterms:contributor>
   <dcterms:contributor>TÁRKI Joint Research Center</dcterms:contributor>
	<dcterms:contributor>Századvég Center for Political Analysis (1.)</dcterms:contributor>
	<dcterms:contributor>The Hungarian Prime Ministers Office (2.)</dcterms:contributor>
	<dcterms:contributor>Hungarian Central Statistical Office Demographic Research Institute (3.)</dcterms:contributor>
   <dcterms:subject>1.1</dcterms:subject>
   <dcterms:subject>2004-03-00: the labels of the data file are corrected and complemented</dcterms:subject>
   <dcterms:description>1. party preferences and political attitudes 2. opinions about the NATO attack agains Yugoslavia and the EU accession of Hungary 3. attitudes towards bearing children, the child-support system and abortion</dcterms:description>
	<dcterms:subject>demography</dcterms:subject>
	<dcterms:subject>social behaviour and attitudes</dcterms:subject>
	<dcterms:subject>family life, marriage, relationship</dcterms:subject>
	<dcterms:subject>mass political behavior, attitudes</dcterms:subject>
	<dcterms:subject>political institutions, public administration</dcterms:subject>
	<dcterms:subject>economic conditions and indicators</dcterms:subject>
	<dcterms:subject>economic policy</dcterms:subject>
	<dcterms:subject>social welfare policy and systems</dcterms:subject>
	<dcterms:subject>childbearing, family planning and abortion</dcterms:subject>
	<dcterms:subject>local society, region</dcterms:subject>
	<dcterms:subject>international politics and organisations</dcterms:subject>
	<dcterms:subject>conflict, security and peace</dcterms:subject>
   <dcterms:subject>1999-05-09  1999-05-23</dcterms:subject>
   <dcterms:coverage>Hungary</dcterms:coverage>
   <dcterms:subject>person</dcterms:subject>
   <dcterms:subject>survey data</dcterms:subject>
   <dcterms:subject>cross-section</dcterms:subject>
   <dcterms:subject>A multi-stage proportionally stratified random probability sample representative of the Hungarian adult population. Unsuccessful inquiries were substituted with supplementary addresses, where persons to be interviewed were selected on the basis of the Leslie Kish key.</dcterms:subject>
   <dcterms:subject>face-to-face interview</dcterms:subject>
   <dcterms:subject>block 1: A, block 2: A, block 3: B</dcterms:subject>
   <dcterms:rights>Publications based on TÁRKI data collections should acknowledge those sources, primary investigators and depositors.</dcterms:rights>
   <dcterms:subject>1518</dcterms:subject>
   <dcterms:subject>126</dcterms:subject>
	<dcterms:subject>SPSS portable datafile</dcterms:subject>
	<dcterms:subject>other study-related materials:</dcterms:subject>
	<dcterms:subject>Hungarian questionnaire</dcterms:subject>
	<dcterms:subject>Hungarian documentation</dcterms:subject>
	<dcterms:subject>English questionnaire</dcterms:subject>
</entry>